dizzy/__init__.py
dizzy/config.py
dizzy/dizz.py
dizzy/dizz_iterator.py
dizzy/dizz_state.py
dizzy/interaction.py
dizzy/interaction_iterator.py
dizzy/interaction_state.py
dizzy/job.py
dizzy/library.py
dizzy/log.py
dizzy/module.py
dizzy/pcap.py
dizzy/profile.py
dizzy/state.py
dizzy/tools.py
dizzy/value.py
dizzy/encodings/__init__.py
dizzy/encodings/der.py
dizzy/encodings/encoding.py
dizzy/functions/__init__.py
dizzy/functions/adv_copy.py
dizzy/functions/call.py
dizzy/functions/checksum.py
dizzy/functions/encryption.py
dizzy/functions/length.py
dizzy/functions/link.py
dizzy/functions/padding.py
dizzy/functions/rand.py
dizzy/functions/run_cmd.py
dizzy/functions/time.py
dizzy/objects/__init__.py
dizzy/objects/field.py
dizzy/objects/list.py
dizzy/objects/rand.py
dizzy/objects/regex.py
dizzy/probe/__init__.py
dizzy/probe/http.py
dizzy/probe/icmp.py
dizzy/probe/tcp.py
dizzy/session/__init__.py
dizzy/session/eth.py
dizzy/session/http.py
dizzy/session/sctp.py
dizzy/session/ssl.py
dizzy/session/stdout-hex.py
dizzy/session/stdout.py
dizzy/session/tcp.py
dizzy/session/udp.py
dizzy-2.0.data/data/share/dizzy/std_string_lib.txt
dizzy-2.0.data/scripts/dizzy_cmd
dizzy-2.0.dist-info/DESCRIPTION.rst
dizzy-2.0.dist-info/METADATA
dizzy-2.0.dist-info/RECORD
dizzy-2.0.dist-info/WHEEL
dizzy-2.0.dist-info/metadata.json
dizzy-2.0.dist-info/top_level.txt
